{
  "id": "2145921",
  "name": "web-things",
  "font_family": "iconfont",
  "css_prefix_text": "icon-",
  "description": "",
  "glyphs": [
    {
      "icon_id": "12320811",
      "name": "菜单",
      "font_class": "caidan1",
      "unicode": "e615",
      "unicode_decimal": 58901
    },
    {
      "icon_id": "17606976",
      "name": "菜单左",
      "font_class": "caidanzuo",
      "unicode": "e6c3",
      "unicode_decimal": 59075
    },
    {
      "icon_id": "17606983",
      "name": "菜单右",
      "font_class": "caidanyou",
      "unicode": "e6c4",
      "unicode_decimal": 59076
    },
    {
      "icon_id": "1554897",
      "name": "菜单",
      "font_class": "caidan",
      "unicode": "e606",
      "unicode_decimal": 58886
    },
    {
      "icon_id": "9514417",
      "name": "收缩菜单-左",
      "font_class": "shousuocaidan",
      "unicode": "e620",
      "unicode_decimal": 58912
    },
    {
      "icon_id": "9600498",
      "name": "收缩菜单-右",
      "font_class": "shousuocaidan-copy",
      "unicode": "e64b",
      "unicode_decimal": 58955
    },
    {
      "icon_id": "495787",
      "name": "home",
      "font_class": "home",
      "unicode": "e64e",
      "unicode_decimal": 58958
    },
    {
      "icon_id": "637629",
      "name": "LC_icon_light_line",
      "font_class": "LC_icon_light_line",
      "unicode": "e629",
      "unicode_decimal": 58921
    },
    {
      "icon_id": "1057265",
      "name": "automation",
      "font_class": "automation",
      "unicode": "e788",
      "unicode_decimal": 59272
    },
    {
      "icon_id": "1294069",
      "name": "设置",
      "font_class": "setting",
      "unicode": "e61f",
      "unicode_decimal": 58911
    },
    {
      "icon_id": "1302623",
      "name": "log",
      "font_class": "log",
      "unicode": "e613",
      "unicode_decimal": 58899
    },
    {
      "icon_id": "1444844",
      "name": "lightbulb",
      "font_class": "lightbulb",
      "unicode": "e7d6",
      "unicode_decimal": 59350
    },
    {
      "icon_id": "1802969",
      "name": "light",
      "font_class": "light",
      "unicode": "e611",
      "unicode_decimal": 58897
    },
    {
      "icon_id": "3750442",
      "name": "Light",
      "font_class": "Light",
      "unicode": "e636",
      "unicode_decimal": 58934
    },
    {
      "icon_id": "8804710",
      "name": "floorplan",
      "font_class": "floorplan",
      "unicode": "e8ed",
      "unicode_decimal": 59629
    },
    {
      "icon_id": "10156402",
      "name": "设置",
      "font_class": "shezhi",
      "unicode": "e654",
      "unicode_decimal": 58964
    },
    {
      "icon_id": "11770076",
      "name": "out",
      "font_class": "out",
      "unicode": "e658",
      "unicode_decimal": 58968
    }
  ]
}
